test/__init__.py
test/test.py
growth_test-0.1.1.dist-info/LICENSE
growth_test-0.1.1.dist-info/METADATA
growth_test-0.1.1.dist-info/WHEEL
growth_test-0.1.1.dist-info/top_level.txt
growth_test-0.1.1.dist-info/RECORD
